{
    "type": "FeatureCollection",
    "generator": "JOSM",
    "features": [
        {
            "type": "Feature",
            "properties": {
                "name": "Tumwater Canyon"
            },
            "geometry": {
                "type": "Point",
                "coordinates": [
                    -120.72086368561,
                    47.61287565091
                ]
            }
        },
        {
            "type": "Feature",
            "properties": {
                "name": "Icicle Canyon"
            },
            "geometry": {
                "type": "Point",
                "coordinates": [
                    -120.75073276520,
                    47.55521374701
                ]
            }
        }
    ]
}